{
  "startingFEN": "rnbqkbnr/pppppppp/8/8/8/8/PPPPPPPP/RNBQKBNR w KQkq - 0 1",
  "openings": [
    {
      "name": "Caro-Kann Defense",
      "key": "CaroKann",
      "information": "The Caro-Kann Defense is a common defense against e4, characterized by d4 and c6. It aims for a solid, yet flexible position.",
      "initialPlayerColor": "b",
      "variations": [
        {
          "name": "Quick Init-CaroKann",
          "key": "QICK",
          "moves": [
            "e4",
            "c6",
            "d4",
            "d5"
          ],
          "commentary": [
            "first move", "sec move", "third move", "four"
          ]
        },
        {
          "name": "Quick Init-CaroKann2",
          "key": "QICK2",
          "moves": [
            "e3",
            "c5",
            "c4",
            "d6"
          ],
          "commentary": [
            "first move2", "sec move2", "third move2", "four2"
          ]
        }
      ]
    }
  ]
}
